dictionary/__init__.py
dictionary/dictionary.py
a3a3_dictionary-2.0.0.dist-info/METADATA
a3a3_dictionary-2.0.0.dist-info/WHEEL
a3a3_dictionary-2.0.0.dist-info/top_level.txt
a3a3_dictionary-2.0.0.dist-info/RECORD
